CHANGES
MANIFEST
README
setup.py
pysphere/__init__.py
pysphere/version.py
pysphere/vi_mor.py
pysphere/vi_performance_manager.py
pysphere/vi_property.py
pysphere/vi_server.py
pysphere/vi_snapshot.py
pysphere/vi_task.py
pysphere/vi_virtual_machine.py
pysphere.egg-info/PKG-INFO
pysphere.egg-info/SOURCES.txt
pysphere.egg-info/dependency_links.txt
pysphere.egg-info/top_level.txt
pysphere/ZSI/LBNLCopyright
pysphere/ZSI/ServiceContainer.py
pysphere/ZSI/ServiceProxy.py
pysphere/ZSI/TC.py
pysphere/ZSI/TCapache.py
pysphere/ZSI/TCcompound.py
pysphere/ZSI/TCnumbers.py
pysphere/ZSI/TCtimes.py
pysphere/ZSI/__init__.py
pysphere/ZSI/address.py
pysphere/ZSI/auth.py
pysphere/ZSI/client.py
pysphere/ZSI/digest_auth.py
pysphere/ZSI/dispatch.py
pysphere/ZSI/fault.py
pysphere/ZSI/parse.py
pysphere/ZSI/resolvers.py
pysphere/ZSI/schema.py
pysphere/ZSI/typeinterpreter.py
pysphere/ZSI/version.py
pysphere/ZSI/writer.py
pysphere/ZSI/generate/__init__.py
pysphere/ZSI/generate/commands.py
pysphere/ZSI/generate/containers.py
pysphere/ZSI/generate/pyclass.py
pysphere/ZSI/generate/utility.py
pysphere/ZSI/generate/wsdl2dispatch.py
pysphere/ZSI/generate/wsdl2python.py
pysphere/ZSI/twisted/WSresource.py
pysphere/ZSI/twisted/WSsecurity.py
pysphere/ZSI/twisted/__init__.py
pysphere/ZSI/twisted/client.py
pysphere/ZSI/twisted/interfaces.py
pysphere/ZSI/twisted/reverse.py
pysphere/ZSI/twisted/wsgi.py
pysphere/ZSI/wstools/MIMEAttachment.py
pysphere/ZSI/wstools/Namespaces.py
pysphere/ZSI/wstools/TimeoutSocket.py
pysphere/ZSI/wstools/UserTuple.py
pysphere/ZSI/wstools/Utility.py
pysphere/ZSI/wstools/WSDLTools.py
pysphere/ZSI/wstools/XMLSchema.py
pysphere/ZSI/wstools/XMLname.py
pysphere/ZSI/wstools/__init__.py
pysphere/ZSI/wstools/c14n.py
pysphere/ZSI/wstools/logging.py
pysphere/resources/VimService_services.py
pysphere/resources/VimService_services_types.py
pysphere/resources/__init__.py
pysphere/resources/vi_exception.py
tests/README.txt
tests/__init__.py
tests/config.ini.dist
tests/test_threading.py
tests/test_vi_property.py
tests/test_vi_server.py