Metadata-Version: 1.0
Name: pysphere
Version: 0.1.6
Summary: Python API for interacting with the vSphere Web Services SDK
Home-page: http://pysphere.googlecode.com
Author: Sebastian Tello
Author-email: argos83@gmail.com
License: New BSD License
Download-URL: http://pysphere.googlecode.com/files/pysphere-0.1.5.zip
Keywords: vSphere,Virtual,vmware,ESX,ESXi,VirtualCenter,SDK,API
Platform: UNKNOWN
Classifier: Programming Language :: Python
Classifier: Programming Language :: Python :: 2.5
Classifier: Programming Language :: Python :: 2.6
Classifier: Programming Language :: Python :: 2.7
Classifier: Operating System :: OS Independent
Classifier: Development Status :: 5 - Production/Stable
Classifier: Environment :: Other Environment
Classifier: Intended Audience :: Developers
Classifier: Intended Audience :: System Administrators
Classifier: Intended Audience :: Science/Research
Classifier: Intended Audience :: Information Technology
Classifier: License :: OSI Approved :: BSD License
Classifier: Topic :: Software Development :: Libraries :: Python Modules
Classifier: Topic :: Software Development :: Quality Assurance
Classifier: Topic :: Software Development :: Testing
Classifier: Topic :: System :: Distributed Computing
Classifier: Topic :: System :: Emulators
Classifier: Topic :: System :: Operating System
Classifier: Topic :: System :: Systems Administration
Classifier: Topic :: Utilities
